{"cameraMode":{"drawMode":0,"name":"Shaded","section":"Shading Mode"},"sceneLighting":true,"audioPlay":false,"sceneViewState":{"m_AlwaysRefresh":false,"showFog":true,"showSkybox":true,"showFlares":true,"showImageEffects":true,"showParticleSystems":true,"showVisualEffectGraphs":true,"m_FxEnabled":true},"in2DMode":false,"pivot":{"x":3.427438974380493,"y":5.539479732513428,"z":-7.8180317878723148},"rotation":{"x":0.16774721443653108,"y":-0.09840472787618637,"z":0.016830939799547197,"w":0.9807635545730591},"size":4.473249912261963,"orthographic":false}